mesa_geo/__init__.py
mesa_geo/geo_base.py
mesa_geo/geoagent.py
mesa_geo/geospace.py
mesa_geo/raster_layers.py
mesa_geo/tile_layers.py
mesa_geo/visualization/__init__.py
mesa_geo/visualization/geojupyter_viz.py
mesa_geo/visualization/leaflet_viz.py
mesa_geo/visualization/components/geospace_component.py
mesa_geo-0.9.2.dist-info/METADATA
mesa_geo-0.9.2.dist-info/WHEEL
mesa_geo-0.9.2.dist-info/entry_points.txt
mesa_geo-0.9.2.dist-info/licenses/LICENSE
mesa_geo-0.9.2.dist-info/licenses/NOTICE
mesa_geo-0.9.2.dist-info/RECORD
