Metadata-Version: 2.4
Name: Mesa-Geo
Version: 0.9.2
Summary: GIS Agent-based modeling (ABM) in Python
Project-URL: homepage, https://github.com/mesa/mesa-geo
Project-URL: repository, https://github.com/mesa/mesa-geo
Author-email: Mesa Team <maintainers@projectmesa.dev>
License: Apache 2.0
License-File: LICENSE
License-File: NOTICE
Keywords: ABM,GIS,agent,based,geographic,information,model,modeling,multi-agent,simulation,systems
Classifier: Development Status :: 3 - Alpha
Classifier: Intended Audience :: Science/Research
Classifier: License :: OSI Approved :: Apache Software License
Classifier: Natural Language :: English
Classifier: Operating System :: OS Independent
Classifier: Programming Language :: Python :: 3 :: Only
Classifier: Programming Language :: Python :: 3.10
Classifier: Programming Language :: Python :: 3.11
Classifier: Programming Language :: Python :: 3.12
Classifier: Topic :: Scientific/Engineering
Classifier: Topic :: Scientific/Engineering :: Artificial Intelligence
Classifier: Topic :: Scientific/Engineering :: Artificial Life
Requires-Python: >=3.10
Requires-Dist: folium
Requires-Dist: geopandas
Requires-Dist: ipyleaflet
Requires-Dist: libpysal
Requires-Dist: mesa[rec]<3.3,>=3.0
Requires-Dist: pyproj
Requires-Dist: rasterio>=1.4b1
Requires-Dist: rtree
Requires-Dist: shapely
Requires-Dist: xyzservices>=2022.9.0
Provides-Extra: dev
Requires-Dist: coverage; extra == 'dev'
Requires-Dist: pytest-cov; extra == 'dev'
Requires-Dist: pytest-mock; extra == 'dev'
Requires-Dist: pytest>=4.6; extra == 'dev'
Requires-Dist: ruff; extra == 'dev'
Requires-Dist: sphinx; extra == 'dev'
Provides-Extra: docs
Requires-Dist: ipython; extra == 'docs'
Requires-Dist: myst-nb; extra == 'docs'
Requires-Dist: myst-parser; extra == 'docs'
Requires-Dist: pydata-sphinx-theme; extra == 'docs'
Requires-Dist: seaborn; extra == 'docs'
Requires-Dist: sphinx; extra == 'docs'
Provides-Extra: examples
Requires-Dist: momepy; extra == 'examples'
Requires-Dist: pytest; extra == 'examples'
